setup.py
kson/__init__.py
kson/command.py
kson.egg-info/PKG-INFO
kson.egg-info/SOURCES.txt
kson.egg-info/dependency_links.txt
kson.egg-info/entry_points.txt
kson.egg-info/requires.txt
kson.egg-info/top_level.txt