Metadata-Version: 1.1
Name: kson
Version: 0.1.0
Summary: Keystripped Schemafied Object Notation
Home-page: http://bitbucket.org/mbarkhau/kson/
Author: Manuel Barkhau
Author-email: mbarkhau@gmail.com
License: BSD License
Keywords: kson json parser javascript schema
Platform: UNKNOWN
Classifier: Development Status :: 4 - Beta
Classifier: Environment :: Console
Classifier: Environment :: Web Environment
Classifier: Intended Audience :: Developers
Classifier: License :: OSI Approved :: BSD License
Classifier: Operating System :: MacOS :: MacOS X
Classifier: Operating System :: POSIX
Classifier: Programming Language :: Python
Classifier: Programming Language :: Python :: 2
Classifier: Programming Language :: Python :: 3
Classifier: Topic :: Utilities
